{
  "openapi": "3.0.4",
  "info": {
    "title": "SEP490_G154_Service",
    "version": "1.0"
  },
  "paths": {
    "/api/HomesStay/FilterHeader": {
      "get": {
        "tags": [
          "HomesStay"
        ],
        "parameters": [
          {
            "name": "checkIn",
            "in": "query",
            "schema": {
              "type": "string",
              "format": "date"
            }
          },
          {
            "name": "checkOut",
            "in": "query",
            "schema": {
              "type": "string",
              "format": "date"
            }
          },
          {
            "name": "guests",
            "in": "query",
            "schema": {
              "type": "integer",
              "format": "int32"
            }
          },
          {
            "name": "rooms",
            "in": "query",
            "schema": {
              "type": "integer",
              "format": "int32"
            }
          }
        ],
        "responses": {
          "200": {
            "description": "OK"
          }
        }
      }
    },
    "/api/Login/Login": {
      "post": {
        "tags": [
          "Login"
        ],
        "parameters": [
          {
            "name": "email",
            "in": "query",
            "schema": {
              "type": "string"
            }
          },
          {
            "name": "password",
            "in": "query",
            "schema": {
              "type": "string"
            }
          }
        ],
        "responses": {
          "200": {
            "description": "OK"
          }
        }
      }
    },
    "/api/Login/RegisterAdmin": {
      "post": {
        "tags": [
          "Login"
        ],
        "requestBody": {
          "content": {
            "application/json": {
              "schema": {
                "$ref": "#/components/schemas/CreateAcc"
              }
            },
            "text/json": {
              "schema": {
                "$ref": "#/components/schemas/CreateAcc"
              }
            },
            "application/*+json": {
              "schema": {
                "$ref": "#/components/schemas/CreateAcc"
              }
            }
          }
        },
        "responses": {
          "200": {
            "description": "OK"
          }
        }
      }
    },
    "/api/Login/RegisterSeller": {
      "post": {
        "tags": [
          "Login"
        ],
        "requestBody": {
          "content": {
            "application/json": {
              "schema": {
                "$ref": "#/components/schemas/CreateAcc"
              }
            },
            "text/json": {
              "schema": {
                "$ref": "#/components/schemas/CreateAcc"
              }
            },
            "application/*+json": {
              "schema": {
                "$ref": "#/components/schemas/CreateAcc"
              }
            }
          }
        },
        "responses": {
          "200": {
            "description": "OK"
          }
        }
      }
    },
    "/api/Login/RegisterHost": {
      "post": {
        "tags": [
          "Login"
        ],
        "requestBody": {
          "content": {
            "application/json": {
              "schema": {
                "$ref": "#/components/schemas/CreateAcc"
              }
            },
            "text/json": {
              "schema": {
                "$ref": "#/components/schemas/CreateAcc"
              }
            },
            "application/*+json": {
              "schema": {
                "$ref": "#/components/schemas/CreateAcc"
              }
            }
          }
        },
        "responses": {
          "200": {
            "description": "OK"
          }
        }
      }
    },
    "/api/Login/RegisterCustomer": {
      "post": {
        "tags": [
          "Login"
        ],
        "requestBody": {
          "content": {
            "application/json": {
              "schema": {
                "$ref": "#/components/schemas/CreateAcc"
              }
            },
            "text/json": {
              "schema": {
                "$ref": "#/components/schemas/CreateAcc"
              }
            },
            "application/*+json": {
              "schema": {
                "$ref": "#/components/schemas/CreateAcc"
              }
            }
          }
        },
        "responses": {
          "200": {
            "description": "OK"
          }
        }
      }
    },
    "/api/Login/LoginWithGoogleSeller": {
      "post": {
        "tags": [
          "Login"
        ],
        "requestBody": {
          "content": {
            "application/json": {
              "schema": {
                "$ref": "#/components/schemas/GoogleLoginDTO"
              }
            },
            "text/json": {
              "schema": {
                "$ref": "#/components/schemas/GoogleLoginDTO"
              }
            },
            "application/*+json": {
              "schema": {
                "$ref": "#/components/schemas/GoogleLoginDTO"
              }
            }
          }
        },
        "responses": {
          "200": {
            "description": "OK"
          }
        }
      }
    },
    "/api/Login/LoginWithGoogleHost": {
      "post": {
        "tags": [
          "Login"
        ],
        "requestBody": {
          "content": {
            "application/json": {
              "schema": {
                "$ref": "#/components/schemas/GoogleLoginDTO"
              }
            },
            "text/json": {
              "schema": {
                "$ref": "#/components/schemas/GoogleLoginDTO"
              }
            },
            "application/*+json": {
              "schema": {
                "$ref": "#/components/schemas/GoogleLoginDTO"
              }
            }
          }
        },
        "responses": {
          "200": {
            "description": "OK"
          }
        }
      }
    },
    "/api/Login/LoginWithGoogleCustomer": {
      "post": {
        "tags": [
          "Login"
        ],
        "requestBody": {
          "content": {
            "application/json": {
              "schema": {
                "$ref": "#/components/schemas/GoogleLoginDTO"
              }
            },
            "text/json": {
              "schema": {
                "$ref": "#/components/schemas/GoogleLoginDTO"
              }
            },
            "application/*+json": {
              "schema": {
                "$ref": "#/components/schemas/GoogleLoginDTO"
              }
            }
          }
        },
        "responses": {
          "200": {
            "description": "OK"
          }
        }
      }
    },
    "/api/Login/LoginWithFacebookSeller": {
      "post": {
        "tags": [
          "Login"
        ],
        "requestBody": {
          "content": {
            "application/json": {
              "schema": {
                "$ref": "#/components/schemas/FacebookLoginDTO"
              }
            },
            "text/json": {
              "schema": {
                "$ref": "#/components/schemas/FacebookLoginDTO"
              }
            },
            "application/*+json": {
              "schema": {
                "$ref": "#/components/schemas/FacebookLoginDTO"
              }
            }
          }
        },
        "responses": {
          "200": {
            "description": "OK"
          }
        }
      }
    },
    "/api/Login/LoginWithFacebookHost": {
      "post": {
        "tags": [
          "Login"
        ],
        "requestBody": {
          "content": {
            "application/json": {
              "schema": {
                "$ref": "#/components/schemas/FacebookLoginDTO"
              }
            },
            "text/json": {
              "schema": {
                "$ref": "#/components/schemas/FacebookLoginDTO"
              }
            },
            "application/*+json": {
              "schema": {
                "$ref": "#/components/schemas/FacebookLoginDTO"
              }
            }
          }
        },
        "responses": {
          "200": {
            "description": "OK"
          }
        }
      }
    },
    "/api/Login/LoginWithFacebookCustomer": {
      "post": {
        "tags": [
          "Login"
        ],
        "requestBody": {
          "content": {
            "application/json": {
              "schema": {
                "$ref": "#/components/schemas/FacebookLoginDTO"
              }
            },
            "text/json": {
              "schema": {
                "$ref": "#/components/schemas/FacebookLoginDTO"
              }
            },
            "application/*+json": {
              "schema": {
                "$ref": "#/components/schemas/FacebookLoginDTO"
              }
            }
          }
        },
        "responses": {
          "200": {
            "description": "OK"
          }
        }
      }
    },
    "/WeatherForecast": {
      "get": {
        "tags": [
          "WeatherForecast"
        ],
        "operationId": "GetWeatherForecast",
        "responses": {
          "200": {
            "description": "OK",
            "content": {
              "text/plain": {
                "schema": {
                  "type": "array",
                  "items": {
                    "$ref": "#/components/schemas/WeatherForecast"
                  }
                }
              },
              "application/json": {
                "schema": {
                  "type": "array",
                  "items": {
                    "$ref": "#/components/schemas/WeatherForecast"
                  }
                }
              },
              "text/json": {
                "schema": {
                  "type": "array",
                  "items": {
                    "$ref": "#/components/schemas/WeatherForecast"
                  }
                }
              }
            }
          }
        }
      }
    }
  },
  "components": {
    "schemas": {
      "CreateAcc": {
        "required": [
          "fullName",
          "password"
        ],
        "type": "object",
        "properties": {
          "email": {
            "pattern": "^[a-zA-Z0-9._%+-]+@(gmail\\.com|fpt\\.edu\\.vn)$",
            "type": "string",
            "nullable": true
          },
          "password": {
            "minLength": 6,
            "pattern": "^(?=.*[a-z])(?=.*[A-Z])(?=.*\\W).+$",
            "type": "string"
          },
          "fullName": {
            "minLength": 1,
            "type": "string"
          },
          "phone": {
            "pattern": "^\\d{10}$",
            "type": "string",
            "nullable": true
          }
        },
        "additionalProperties": false
      },
      "FacebookLoginDTO": {
        "type": "object",
        "properties": {
          "accessToken": {
            "type": "string",
            "nullable": true
          }
        },
        "additionalProperties": false
      },
      "GoogleLoginDTO": {
        "type": "object",
        "properties": {
          "idToken": {
            "type": "string",
            "nullable": true
          }
        },
        "additionalProperties": false
      },
      "WeatherForecast": {
        "type": "object",
        "properties": {
          "date": {
            "type": "string",
            "format": "date"
          },
          "temperatureC": {
            "type": "integer",
            "format": "int32"
          },
          "temperatureF": {
            "type": "integer",
            "format": "int32",
            "readOnly": true
          },
          "summary": {
            "type": "string",
            "nullable": true
          }
        },
        "additionalProperties": false
      }
    }
  }
}